imarkdown/__init__.py
imarkdown/config.py
imarkdown/constant.py
imarkdown/converter.py
imarkdown/schema.py
imarkdown/adapter/__init__.py
imarkdown/adapter/aliyun_adapter.py
imarkdown/adapter/base.py
imarkdown/adapter/local_adapter.py
imarkdown/client/__init__.py
imarkdown/utils/__init__.py
imarkdown/utils/cache.py
imarkdown/utils/singleton.py
imarkdown-1.2.1.dist-info/METADATA
imarkdown-1.2.1.dist-info/WHEEL
imarkdown-1.2.1.dist-info/top_level.txt
imarkdown-1.2.1.dist-info/RECORD
