Metadata-Version: 2.1
Name: imarkdown
Version: 1.2.1
Summary: A practical Markdown image url converter
Home-page: https://github.com/Undertone0809/imarkdown
Author: Zeeland
Author-email: zeeland@foxmail.com
License: Apache 2.0
Keywords: Markdown,markdown,imarkdown,markdown converter
Classifier: Development Status :: 3 - Alpha
Classifier: Intended Audience :: Developers
Classifier: Programming Language :: Python :: 3
Classifier: Programming Language :: Python :: 3.7
Classifier: Programming Language :: Python :: 3.8
Classifier: Programming Language :: Python :: 3.9
Classifier: Programming Language :: Python :: 3.10
Classifier: Programming Language :: Python :: 3 :: Only
Classifier: License :: OSI Approved :: MIT License
Classifier: Operating System :: OS Independent
Requires-Dist: requests
Requires-Dist: pydantic (~=1.10.0)
Requires-Dist: cushy-storage
Requires-Dist: broadcast-service (==1.3.2)
